google_weather/__init__.py
google_weather/colab.py
google_weather/lang.py
google_weather/weather.py
pygoogleweather-0.1.12.dist-info/METADATA
pygoogleweather-0.1.12.dist-info/WHEEL
pygoogleweather-0.1.12.dist-info/top_level.txt
pygoogleweather-0.1.12.dist-info/RECORD
