Metadata-Version: 2.2
Name: pygoogleweather
Version: 0.1.12
Summary: Python library to get weather from Google Search. No API keys required.
Home-page: https://github.com/jpmanson/google-weather
Author: Juan Pablo Manson
Author-email: jpmanson@gmail.com
Requires-Python: >=3.9
Requires-Dist: playwright>=1.41.0
Requires-Dist: beautifulsoup4>=4.10.0
Requires-Dist: html5lib>=1.1
Requires-Dist: lxml>=4.9.0
Requires-Dist: nest-asyncio>=1.5.8
Dynamic: author
Dynamic: author-email
Dynamic: description
Dynamic: description-content-type
Dynamic: home-page
Dynamic: requires-dist
Dynamic: requires-python
Dynamic: summary
